setup.py
ustcjiaqi/__init__.py
ustcjiaqi/get_score.py
ustcjiaqi.egg-info/PKG-INFO
ustcjiaqi.egg-info/SOURCES.txt
ustcjiaqi.egg-info/dependency_links.txt
ustcjiaqi.egg-info/requires.txt
ustcjiaqi.egg-info/top_level.txt