Metadata-Version: 1.0
Name: ustcjiaqi
Version: 2.2.3
Summary: This is ustcjiaqi score package
Home-page: https://github.com/WolverineQin/ustciscr
Author: qjqqjq
Author-email: 1102692995@qq.com
License: MIT Licence
Keywords: pip,ustcjiaqi,featureextraction
Platform: any
